{
  "date" : "Sun, 09 Nov, 2025 18:37:51 +0000",
  "doco" : "For each file: start is seconds after start activity occurred. Length = milliseconds activity took",
  "files" : [
    {
      "name" : "/fsh-generated/resources/ImplementationGuide-hl7.fhir.no.hackathon.2025.json",
      "size" : 3168,
      "processes" : [
        {
          "activity" : "load",
          "start" : 39,
          "length" : 27
        },
        {
          "activity" : "checkR4R4B",
          "start" : 40,
          "length" : 9
        },
        {
          "activity" : "generateNarratives",
          "start" : 40,
          "length" : 103
        },
        {
          "activity" : "validate",
          "start" : 43,
          "length" : 2345
        },
        {
          "activity" : "checkConformanceResources",
          "start" : 45,
          "length" : 1
        },
        {
          "activity" : "generate1",
          "start" : 45,
          "length" : 56
        },
        {
          "activity" : "generate2",
          "start" : 48,
          "length" : 63
        },
        {
          "activity" : "generateValidationPack",
          "start" : 58,
          "length" : 3
        }
      ]
    },
    {
      "name" : "fsh-generated/resources/Patient-Pasient-1.json",
      "size" : 375,
      "processes" : [
        {
          "activity" : "loadResources",
          "start" : 39,
          "length" : 12
        },
        {
          "activity" : "load-configure",
          "start" : 40,
          "length" : 1
        },
        {
          "activity" : "generateNarratives",
          "start" : 40,
          "length" : 349
        },
        {
          "activity" : "validate",
          "start" : 45,
          "length" : 6
        },
        {
          "activity" : "generate1",
          "start" : 45,
          "length" : 14
        },
        {
          "activity" : "generate2",
          "start" : 48,
          "length" : 13
        }
      ]
    },
    {
      "name" : "fsh-generated/resources/StructureDefinition-mal-observation-blodprove.json",
      "size" : 2253,
      "processes" : [
        {
          "activity" : "loadResources",
          "start" : 39,
          "length" : 11
        },
        {
          "activity" : "load",
          "start" : 39,
          "length" : 21
        },
        {
          "activity" : "generateSnapshots",
          "start" : 39,
          "length" : 55
        },
        {
          "activity" : "generateNarratives",
          "start" : 41,
          "length" : 112
        },
        {
          "activity" : "validate",
          "start" : 41,
          "length" : 1367
        },
        {
          "activity" : "scanForUsageStats",
          "start" : 45,
          "length" : 2
        },
        {
          "activity" : "generate1",
          "start" : 45,
          "length" : 113
        },
        {
          "activity" : "generate2",
          "start" : 48,
          "length" : 861
        },
        {
          "activity" : "generate2",
          "start" : 50,
          "length" : 1301
        },
        {
          "activity" : "generateValidationPack",
          "start" : 58,
          "length" : 11
        },
        {
          "activity" : "scanExamplesForR5",
          "start" : 64,
          "length" : 1
        }
      ]
    },
    {
      "name" : "fsh-generated/resources/StructureDefinition-mal-patient.json",
      "size" : 829,
      "processes" : [
        {
          "activity" : "loadResources",
          "start" : 39,
          "length" : 12
        },
        {
          "activity" : "load",
          "start" : 39,
          "length" : 17
        },
        {
          "activity" : "generateSnapshots",
          "start" : 39,
          "length" : 101
        },
        {
          "activity" : "generateNarratives",
          "start" : 41,
          "length" : 49
        },
        {
          "activity" : "validate",
          "start" : 42,
          "length" : 647
        },
        {
          "activity" : "scanForUsageStats",
          "start" : 45,
          "length" : 1
        },
        {
          "activity" : "generate1",
          "start" : 46,
          "length" : 150
        },
        {
          "activity" : "generate2",
          "start" : 49,
          "length" : 970
        },
        {
          "activity" : "generate2",
          "start" : 51,
          "length" : 391
        },
        {
          "activity" : "generateValidationPack",
          "start" : 58,
          "length" : 19
        },
        {
          "activity" : "scanProfilesForR5",
          "start" : 64,
          "length" : 1
        },
        {
          "activity" : "scanExamplesForR5",
          "start" : 64,
          "length" : 1
        }
      ]
    },
    {
      "name" : "/fsh-generated/includes/fsh-link-references.md",
      "size" : 160
    },
    {
      "name" : "/fsh-generated/includes/menu.xml",
      "size" : 1876
    },
    {
      "name" : "/input/pagecontent/ig-publishing.md",
      "size" : 2396
    },
    {
      "name" : "/input/pagecontent/hack-agenda.md",
      "size" : 2976,
      "processes" : [
        {
          "activity" : "generate2",
          "start" : 50,
          "length" : 1
        }
      ]
    },
    {
      "name" : "/input/pagecontent/track-descriptions.md",
      "size" : 7668,
      "processes" : [
        {
          "activity" : "scan",
          "start" : 40,
          "length" : 1
        }
      ]
    },
    {
      "name" : "/input/pagecontent/practical-info.md",
      "size" : 1607
    },
    {
      "name" : "/input/pagecontent/terminology.md",
      "size" : 2324
    },
    {
      "name" : "/input/pagecontent/index.md",
      "size" : 4433
    },
    {
      "name" : "/input/pagecontent/pre-agenda.md",
      "size" : 4119
    },
    {
      "name" : "/template/config",
      "size" : 0
    },
    {
      "name" : "/template/config/_config.yml",
      "size" : 140
    },
    {
      "name" : "/input/images",
      "size" : 0,
      "processes" : [
        {
          "activity" : "makeDependencies",
          "start" : 53,
          "length" : 1
        }
      ]
    },
    {
      "name" : "/input/images/FHIR-Hackathon-pre-meeting-1.ics",
      "size" : 12934
    },
    {
      "name" : "/input/images/test.puml",
      "size" : 389
    },
    {
      "name" : "/input/images/test.svg",
      "size" : 9068
    },
    {
      "name" : "/input/images/FHIR-Hackathon-pre-meeting-2.ics",
      "size" : 12651
    },
    {
      "name" : "/input/images/motesenter.png",
      "size" : 283545
    },
    {
      "name" : "/input/images/rom-A5.png",
      "size" : 1176631,
      "processes" : [
        {
          "activity" : "generate2",
          "start" : 50,
          "length" : 1
        }
      ]
    },
    {
      "name" : "/input/images/FHIR-Hackathon-2025-premeeting-2.pdf",
      "size" : 2521100,
      "processes" : [
        {
          "activity" : "generate2",
          "start" : 50,
          "length" : 2
        }
      ]
    },
    {
      "name" : "/input/images/FHIR-Hackathon-2025-pre1.pdf",
      "size" : 2424894,
      "processes" : [
        {
          "activity" : "generate2",
          "start" : 50,
          "length" : 1
        }
      ]
    },
    {
      "name" : "/temp/pages/_includes/artifacts.xml",
      "size" : 2479
    }
  ]
}
